LICENSE
MANIFEST.in
README.md
requirements.txt
setup.py
bcf/__init__.py
bcf/__main__.py
bcf/cli.py
bcf/ftdi.py
bcf/utils.py
bcf.egg-info/PKG-INFO
bcf.egg-info/SOURCES.txt
bcf.egg-info/dependency_links.txt
bcf.egg-info/entry_points.txt
bcf.egg-info/not-zip-safe
bcf.egg-info/requires.txt
bcf.egg-info/top_level.txt
bcf/firmware/FirmwareList.py
bcf/firmware/GithubApi.py
bcf/firmware/__init__.py
bcf/firmware/utils.py
bcf/firmware/yml_schema.py
bcf/flasher/__init__.py
bcf/flasher/dfu.py
bcf/flasher/uart.py
bcf/flasher/serialport/__init__.py
bcf/flasher/serialport/bridge.py
bcf/flasher/serialport/error.py
bcf/flasher/serialport/ftdi.py
bcf/log/__init__.py
bcf/log/log.py
bcf/repos/__init__.py
bcf/repos/github.py