Metadata-Version: 2.1
Name: bcf
Version: 1.8.1
Summary: BigClown Firmware Tool.
Home-page: https://github.com/bigclownlabs/bch-firmware-tool
Author: HARDWARIO s.r.o.
Author-email: karel.blavka@bigclown.com
License: MIT
Keywords: BigClown,bcf,firmware,flasher
Platform: UNKNOWN
Classifier: Development Status :: 5 - Production/Stable
Classifier: License :: OSI Approved :: MIT License
Classifier: Operating System :: OS Independent
Classifier: Programming Language :: Python
Classifier: Programming Language :: Python :: 2
Classifier: Programming Language :: Python :: 3
Classifier: Topic :: Utilities
Classifier: Environment :: Console
License-File: LICENSE
